README.md
setup.py
pyrti/__init__.py
pyrti/config.py
pyrti/login.py
pyrti/rti.py
pyrti.egg-info/PKG-INFO
pyrti.egg-info/SOURCES.txt
pyrti.egg-info/dependency_links.txt
pyrti.egg-info/requires.txt
pyrti.egg-info/top_level.txt