Metadata-Version: 2.1
Name: pyrti
Version: 0.0.6
Summary: RTIntegration (rti) - Python interface to Request Tracker API REST 2.0
Home-page: https://github.com/infopontes/rti
Author: Marcelo Pontes Rodrigues
Author-email: infopontes@gmail.com
License: MIT License
Keywords: Package,RT,Python
Platform: UNKNOWN
